interpreter/__init__.py
interpreter/archive/(wip)_model_explorer.py
interpreter/archive/cli.py
interpreter/archive/code_block.py
interpreter/archive/code_interpreter.py
interpreter/archive/get_hf_llm.py
interpreter/archive/interpreter.py
interpreter/archive/message_block.py
interpreter/archive/README.md
interpreter/archive/system_message.txt
interpreter/archive/utils.py
interpreter/cli/__init__.py
interpreter/cli/cli.py
interpreter/code_interpreters/__init__.py
interpreter/code_interpreters/base_code_interpreter.py
interpreter/code_interpreters/create_code_interpreter.py
interpreter/code_interpreters/languages/__init__.py
interpreter/code_interpreters/languages/applescript.py
interpreter/code_interpreters/languages/html.py
interpreter/code_interpreters/languages/javascript.py
interpreter/code_interpreters/languages/python.py
interpreter/code_interpreters/languages/r.py
interpreter/code_interpreters/languages/shell.py
interpreter/code_interpreters/subprocess_code_interpreter.py
interpreter/config.yaml
interpreter/core/__init__.py
interpreter/core/core.py
interpreter/core/respond.py
interpreter/llm/__init__.py
interpreter/llm/convert_to_coding_llm.py
interpreter/llm/setup_llm.py
interpreter/llm/setup_local_text_llm.py
interpreter/llm/setup_openai_coding_llm.py
interpreter/llm/setup_text_llm.py
interpreter/rag/__init__.py
interpreter/rag/get_relevant_procedures.py
interpreter/terminal_interface/__init__.py
interpreter/terminal_interface/components/base_block.py
interpreter/terminal_interface/components/code_block.py
interpreter/terminal_interface/components/message_block.py
interpreter/terminal_interface/conversation_navigator.py
interpreter/terminal_interface/magic_commands.py
interpreter/terminal_interface/render_past_conversation.py
interpreter/terminal_interface/terminal_interface.py
interpreter/terminal_interface/validate_llm_settings.py
interpreter/utils/__init__.py
interpreter/utils/check_for_update.py
interpreter/utils/convert_to_openai_messages.py
my_interpreter-0.1.8.1.dist-info/entry_points.txt
my_interpreter-0.1.8.1.dist-info/LICENSE
my_interpreter-0.1.8.1.dist-info/METADATA
my_interpreter-0.1.8.1.dist-info/WHEEL
my_interpreter-0.1.8.1.dist-info/RECORD
