Metadata-Version: 2.1
Name: my-interpreter
Version: 0.1.8.1
Summary: Let language models run code locally.
Author: Willam Wei
Author-email: 9725712@qq.com
Requires-Python: >=3.10,<4.0
Classifier: Programming Language :: Python :: 3
Classifier: Programming Language :: Python :: 3.10
Classifier: Programming Language :: Python :: 3.11
Requires-Dist: appdirs (>=1.4.4,<2.0.0)
Requires-Dist: astor (>=0.8.1,<0.9.0)
Requires-Dist: git-python (>=1.0.3,<2.0.0)
Requires-Dist: huggingface-hub (>=0.16.4,<0.17.0)
Requires-Dist: inquirer (>=3.1.3,<4.0.0)
Requires-Dist: litellm (>=0.1.590,<0.2.0)
Requires-Dist: openai (>=0.28.0,<0.29.0)
Requires-Dist: pyreadline3 (>=3.4.1,<4.0.0) ; sys_platform == "win32"
Requires-Dist: python-dotenv (>=1.0.0,<2.0.0)
Requires-Dist: pyyaml (>=6.0.1,<7.0.0)
Requires-Dist: rich (>=13.4.2,<14.0.0)
Requires-Dist: six (>=1.16.0,<2.0.0)
Requires-Dist: tiktoken (>=0.4.0,<0.5.0)
Requires-Dist: tokentrim (>=0.1.9,<0.2.0)
Requires-Dist: wget (>=3.2,<4.0)
